[
    {
        "key": "dbln",
        "value": "%7B%2261578634555817%22%3A%22QVDC75ao%22%7D",
        "domain": "facebook.com",
        "path": "/login/device-based/",
        "hostOnly": false,
        "creation": "2025-09-11T15:15:23.455Z",
        "lastAccessed": "2025-09-11T15:15:23.455Z"
    },
    {
        "key": "datr",
        "value": "D5bCaE7WuEQNsdM76VuVO0lW",
        "domain": "facebook.com",
        "path": "/",
        "hostOnly": false,
        "creation": "2025-09-11T15:15:23.455Z",
        "lastAccessed": "2025-09-11T15:15:23.455Z"
    },
    {
        "key": "sb",
        "value": "D5bCaESFzHW0OSPtaNiAOS8B",
        "domain": "facebook.com",
        "path": "/",
        "hostOnly": false,
        "creation": "2025-09-11T15:15:23.455Z",
        "lastAccessed": "2025-09-11T15:15:23.455Z"
    },
    {
        "key": "locale",
        "value": "hi_IN",
        "domain": "facebook.com",
        "path": "/",
        "hostOnly": false,
        "creation": "2025-09-11T15:15:23.455Z",
        "lastAccessed": "2025-09-11T15:15:23.455Z"
    },
    {
        "key": "vpd",
        "value": "v1%3B826x424x2.549999952316284",
        "domain": "facebook.com",
        "path": "/",
        "hostOnly": false,
        "creation": "2025-09-11T15:15:23.455Z",
        "lastAccessed": "2025-09-11T15:15:23.455Z"
    },
    {
        "key": "dpr",
        "value": "2.549999952316284",
        "domain": "facebook.com",
        "path": "/",
        "hostOnly": false,
        "creation": "2025-09-11T15:15:23.455Z",
        "lastAccessed": "2025-09-11T15:15:23.455Z"
    },
    {
        "key": "c_user",
        "value": "61578634555817",
        "domain": "facebook.com",
        "path": "/",
        "hostOnly": false,
        "creation": "2025-09-11T15:15:23.455Z",
        "lastAccessed": "2025-09-11T15:15:23.455Z"
    },
    {
        "key": "xs",
        "value": "8%3A8lcQVqDmniXQFw%3A2%3A1757594363%3A-1%3A-1",
        "domain": "facebook.com",
        "path": "/",
        "hostOnly": false,
        "creation": "2025-09-11T15:15:23.455Z",
        "lastAccessed": "2025-09-11T15:15:23.455Z"
    },
    {
        "key": "pas",
        "value": "61579589454986%3AUHEzb7s3mJ%2C61578634555817%3AMqPkVkTixg",
        "domain": "facebook.com",
        "path": "/",
        "hostOnly": false,
        "creation": "2025-09-11T15:15:23.455Z",
        "lastAccessed": "2025-09-11T15:15:23.455Z"
    },
    {
        "key": "ps_l",
        "value": "1",
        "domain": "facebook.com",
        "path": "/",
        "hostOnly": false,
        "creation": "2025-09-11T15:15:23.455Z",
        "lastAccessed": "2025-09-11T15:15:23.455Z"
    },
    {
        "key": "ps_n",
        "value": "1",
        "domain": "facebook.com",
        "path": "/",
        "hostOnly": false,
        "creation": "2025-09-11T15:15:23.455Z",
        "lastAccessed": "2025-09-11T15:15:23.455Z"
    },
    {
        "key": "wd",
        "value": "980x1908",
        "domain": "facebook.com",
        "path": "/",
        "hostOnly": false,
        "creation": "2025-09-11T15:15:23.455Z",
        "lastAccessed": "2025-09-11T15:15:23.455Z"
    },
    {
        "key": "fr",
        "value": "0NlVvBffJDzyGyHxX.AWdcZpLlqyEvtWQAUMUc6WT7yEZIP4iwtEt2E22xZuilVVc9ivU.BowpYP..AAA.0.0.BowueI.AWeJg5WoLDu9xGJYhI4I85ts17A",
        "domain": "facebook.com",
        "path": "/",
        "hostOnly": false,
        "creation": "2025-09-11T15:15:23.455Z",
        "lastAccessed": "2025-09-11T15:15:23.455Z"
    },
    {
        "key": "fbl_st",
        "value": "101038205%3BT%3A29293395",
        "domain": "facebook.com",
        "path": "/",
        "hostOnly": false,
        "creation": "2025-09-11T15:15:23.455Z",
        "lastAccessed": "2025-09-11T15:15:23.455Z"
    },
    {
        "key": "wl_cbv",
        "value": "v2%3Bclient_version%3A2919%3Btimestamp%3A1757603720",
        "domain": "facebook.com",
        "path": "/",
        "hostOnly": false,
        "creation": "2025-09-11T15:15:23.455Z",
        "lastAccessed": "2025-09-11T15:15:23.455Z"
    }
]

